onegov.town-1.15.10-py3.6-nspkg.pth
onegov/town/.gitignore
onegov/town/__init__.py
onegov/town/app.py
onegov/town/homepage_widgets.py
onegov/town/initial_content.py
onegov/town/upgrade.py
onegov/town/content/de.yaml
onegov/town/content/fr.yaml
onegov/town/content/images/38hrjv7gg2w-eric-jan-van-dorp.jpg
onegov/town/content/images/bhnxfaencti-eddy-klaus.jpg
onegov/town/content/images/himwr1n0dzq-martin-sattler.jpg
onegov/town/content/images/nothrvstw70-marc-wieland.jpg
onegov/town/content/images/p0sruan6cfi-samuel-zeller.jpg
onegov/town/forms/builtin/de/abmeldung_wegzug_ausland.form
onegov/town/forms/builtin/de/abmeldung_wegzug_inland.form
onegov/town/forms/builtin/de/abstimmungs_wahlunterlagen.form
onegov/town/forms/builtin/de/anmeldung_zuzug.form
onegov/town/forms/builtin/de/betreibungsregisterauszug.form
onegov/town/forms/builtin/de/eheschein.form
onegov/town/forms/builtin/de/einzahlungsscheine_steuern.form
onegov/town/forms/builtin/de/familienausweis.form
onegov/town/forms/builtin/de/fristerstreckung_steuererklaerung_juristische_person.form
onegov/town/forms/builtin/de/fristerstreckung_steuererklaerung_natuerliche_person.form
onegov/town/forms/builtin/de/geburtsschein.form
onegov/town/forms/builtin/de/handlungsfaehigkeitszeugnis.form
onegov/town/forms/builtin/de/leumundszeugnis.form
onegov/town/forms/builtin/de/steuererklaerungsformulare_juristische_person.form
onegov/town/forms/builtin/de/steuererklaerungsformulare_natuerliche_person.form
onegov/town/forms/builtin/de/todesschein.form
onegov/town/forms/builtin/de/umzug_gemeinde.form
onegov/town/forms/builtin/de/wochenaufenthalt.form
onegov/town/forms/builtin/de/wohnsitzbestaetigung.form
onegov/town/forms/builtin/fr/inscription.form
onegov/town/locale/de_ch/LC_MESSAGES/onegov.town.po
onegov/town/locale/fr_CH/LC_MESSAGES/onegov.town.po
onegov/town/templates/.gitignore
onegov/town/tests/conftest.py
onegov/town/tests/test_initial_content.py
onegov/town/tests/test_views.py
onegov/town/theme/__init__.py
onegov.town-1.15.10.dist-info/METADATA
onegov.town-1.15.10.dist-info/WHEEL
onegov.town-1.15.10.dist-info/entry_points.txt
onegov.town-1.15.10.dist-info/namespace_packages.txt
onegov.town-1.15.10.dist-info/top_level.txt
onegov.town-1.15.10.dist-info/RECORD
