Metadata-Version: 2.1
Name: onegov.town
Version: 1.15.10
Summary: OneGov web application for small towns.
Home-page: http://github.com/onegov/onegov.town
Author: Seantis GmbH
Author-email: info@seantis.ch
License: GPLv2
Platform: any
Classifier: Intended Audience :: Developers
Classifier: Programming Language :: Python :: 3 :: Only
Classifier: Programming Language :: Python :: 3.6
Classifier: Programming Language :: Python :: 3.7
Classifier: Topic :: Software Development :: Libraries :: Python Modules
Classifier: License :: OSI Approved :: GNU General Public License v2 (GPLv2)
Requires-Python: >=3.6
Requires-Dist: onegov.org (>=0.5.0)
Provides-Extra: test
Requires-Dist: coverage ; extra == 'test'
Requires-Dist: morepath ; extra == 'test'
Requires-Dist: freezegun ; extra == 'test'
Requires-Dist: onegov-testing ; extra == 'test'
Requires-Dist: webtest ; extra == 'test'
Requires-Dist: pyquery ; extra == 'test'
Requires-Dist: pytest-localserver ; extra == 'test'
